MANIFEST.in
README.md
setup.cfg
setup.py
docs/CHANGES.rst
docs/CONTRIBUTORS.rst
docs/EXAMPLES.rst
docs/HISTORY.rst
incolumepy/__init__.py
incolumepy.exceptions.egg-info/PKG-INFO
incolumepy.exceptions.egg-info/SOURCES.txt
incolumepy.exceptions.egg-info/dependency_links.txt
incolumepy.exceptions.egg-info/entry_points.txt
incolumepy.exceptions.egg-info/namespace_packages.txt
incolumepy.exceptions.egg-info/not-zip-safe
incolumepy.exceptions.egg-info/requires.txt
incolumepy.exceptions.egg-info/top_level.txt
incolumepy/exceptions/__init__.py