Metadata-Version: 1.1
Name: incolumepy.exceptions
Version: 0.3.0
Summary: pacote de exceções para incolumepy
Home-page: http://www.incolume.com.br
Author: @britodfbr
Author-email: contato@incolume.com.br
License: BSD
Project-URL: Documentation, https://gitlab.com/development-incolume/incolumepy.exceptions/wikis/home
Project-URL: Funding, None
Project-URL: Say Thanks!, None
Project-URL: Source, https://gitlab.com/development-incolume/incolumepy.exceptions
Project-URL: Git, https://gitlab.com/development-incolume/incolumepy.exceptions.git
Project-URL: Tracker, https://gitlab.com/development-incolume/incolumepy.exceptions/issues
Project-URL: Oficial, https://pypi.org/project/incolumepy.exceptions/
Keywords: python incolumepy exceptions exception
Platform: UNKNOWN
Classifier: Development Status :: 5 - Production/Stable
Classifier: Operating System :: OS Independent
Classifier: Natural Language :: Portuguese (Brazilian)
Classifier: Programming Language :: Python
Classifier: Topic :: Software Development :: Libraries :: Python Modules
Classifier: Topic :: Utilities
